[
  {
    "version": "0.1.0",
    "category": "TODO",
    "tags": [
      "TODO"
    ],
    "description": "TODO",
    "completions": null,
    "keybindings": null,
    "aliases": null,
    "dotdir": null,
    "ignore": null,
    "just": null,
    "env": null,
    "loc": 0,
    "xdg": {
      "bin": null,
      "data": null,
      "cache": null,
      "state": null,
      "config": null
    },
    "paths": null,
    "functions": null,
    "dependencies": [
      {
        "kind": "binary|env|file|arch|platform",
        "var": "TODO"
      }
    ],
    "url": {
      "contribute": "TODO",
      "bugz": "TODO",
      "docs": "TODO"
    },
    "templates": [
      "TODO"
    ],
    "health_checks": [
      "TODO"
    ],
    "generates": [
      "TODO"
    ],
    "platform_overrides": {},
    "id": "06188FB7-52DC-46F1-AEAB-2F4A3DB69F99",
    "path": "op/plugins/"
  }
]
